pyBloxyCola/__init__.py
pyBloxyCola/pyBloxy.py
pyBloxyCola-0.1.2.dist-info/METADATA
pyBloxyCola-0.1.2.dist-info/WHEEL
pyBloxyCola-0.1.2.dist-info/top_level.txt
pyBloxyCola-0.1.2.dist-info/RECORD
