Metadata-Version: 2.1
Name: pyBloxyCola
Version: 0.1.2
Summary: An Library that interacts with the Roblox API.
Home-page: https://github.com/lucaytpols/pyBloxy
Author: Illgyaz
License: BSD 2-clause
Platform: UNKNOWN
Classifier: Development Status :: 1 - Planning
Classifier: Intended Audience :: Science/Research
Classifier: License :: OSI Approved :: BSD License
Classifier: Operating System :: POSIX :: Linux
Classifier: Programming Language :: Python :: 3.8
Requires-Dist: requests
